alignak_checks_elasticsearch/__init__.py
alignak_checks_elasticsearch-1.2.0.data/data/share/alignak/etc/arbiter/packs/elasticsearch/commands.cfg
alignak_checks_elasticsearch-1.2.0.data/data/share/alignak/etc/arbiter/packs/elasticsearch/groups.cfg
alignak_checks_elasticsearch-1.2.0.data/data/share/alignak/etc/arbiter/packs/elasticsearch/templates.cfg
alignak_checks_elasticsearch-1.2.0.data/data/share/alignak/etc/backend-json/elasticsearch/commands.json
alignak_checks_elasticsearch-1.2.0.data/data/share/alignak/etc/backend-json/elasticsearch/hostgroups.json
alignak_checks_elasticsearch-1.2.0.data/data/share/alignak/etc/backend-json/elasticsearch/hosts-templates.json
alignak_checks_elasticsearch-1.2.0.data/data/share/alignak/etc/backend-json/elasticsearch/servicegroups.json
alignak_checks_elasticsearch-1.2.0.data/data/share/alignak/etc/backend-json/elasticsearch/services-templates.json
alignak_checks_elasticsearch-1.2.0.data/data/share/alignak/etc/backend-json/elasticsearch/setup.sh
alignak_checks_elasticsearch-1.2.0.data/data/share/alignak/libexec/LICENSE
alignak_checks_elasticsearch-1.2.0.data/data/share/alignak/libexec/README.md
alignak_checks_elasticsearch-1.2.0.data/data/share/alignak/libexec/check_elasticsearch
alignak_checks_elasticsearch-1.2.0.data/data/share/alignak/libexec/check_elasticsearch.conf
alignak_checks_elasticsearch-1.2.0.dist-info/LICENSE
alignak_checks_elasticsearch-1.2.0.dist-info/METADATA
alignak_checks_elasticsearch-1.2.0.dist-info/WHEEL
alignak_checks_elasticsearch-1.2.0.dist-info/top_level.txt
alignak_checks_elasticsearch-1.2.0.dist-info/RECORD
